dgex/__init__.py
dgex-0.0.0.dist-info/LICENSE
dgex-0.0.0.dist-info/METADATA
dgex-0.0.0.dist-info/WHEEL
dgex-0.0.0.dist-info/top_level.txt
dgex-0.0.0.dist-info/RECORD
